LICENSE.md
MANIFEST.in
README.md
dynamic_extras_require.txt
dynamic_install_requires.txt
quicklib_incorporated.v2.5.zip
quicklib_setup_from_yml.py
epic/lab/__init__.py
epic/lab/__main__.py
epic/lab/__version__.py
epic/lab/ipython_startup.py
epic/lab/main.py
epic/lab/pdb.py
epic/lab/shorthand.py
epic/lab/synccode.py
epic/lab/scripts/epic-notebook
epic/lab/scripts/epic-synccode
epic/lab/tests/__init__.py
epic/lab/tests/helpers.py
epic/lab/tests/test_synccode.py
epic/lab/vmsetup/common.sh
epic/lab/vmsetup/on_create.sh
epic/lab/vmsetup/on_resume.sh
epic/lab/vmsetup/on_start.sh
epic_lab.egg-info/PKG-INFO
epic_lab.egg-info/SOURCES.txt
epic_lab.egg-info/dependency_links.txt
epic_lab.egg-info/entry_points.txt
epic_lab.egg-info/top_level.txt