Metadata-Version: 2.1
Name: epic-lab
Version: 1.0.14
Summary: Opinionated research lab management tools
Home-page: https://github.com/Cybereason/epic-lab
Author: Yonatan Perry, Assaf Ben-David, Uri Sternfeld
License: MIT License
Classifier: Development Status :: 4 - Beta
Classifier: Intended Audience :: Developers
Classifier: Operating System :: POSIX :: Linux
Classifier: Operating System :: MacOS :: MacOS X
Classifier: Operating System :: Microsoft :: Windows
Classifier: Programming Language :: Python :: 3 :: Only
Classifier: Programming Language :: Python :: 3.10
Requires-Python: >=3.10
License-File: LICENSE.md
